w3bch3ck
