Metadata-Version: 2.1
Name: w3bch3ck
Version: 1.0.7
Summary: Package for primary check for web service.
Home-page: UNKNOWN
Author: Anzhela
Author-email: dev.anzhela@gmail.com
License: UNKNOWN
Platform: UNKNOWN
Classifier: Programming Language :: Python :: 3
Classifier: Operating System :: OS Independent
Requires-Python: >=3.4
